LICENSE
README.md
setup.py
CrypticCreations/__init__.py
CrypticCreations/cipher_creation.py
CrypticCreations/creations.py
CrypticCreations/random_creation.py
CrypticCreations.egg-info/PKG-INFO
CrypticCreations.egg-info/SOURCES.txt
CrypticCreations.egg-info/dependency_links.txt
CrypticCreations.egg-info/not-zip-safe
CrypticCreations.egg-info/top_level.txt
CrypticCreations/ciphers/__init__.py
CrypticCreations/ciphers/affine.py
CrypticCreations/ciphers/caeser.py
CrypticCreations/ciphers/rot13.py
CrypticCreations/ciphers/tools.py
tests/__init__.py
tests/test_caeser.py