Metadata-Version: 2.1
Name: CrypticCreations
Version: 0.3.1
Summary: Create ciphers or random strings for DnD players to try and read aloud for the group.
Home-page: https://github.com/ClutchTech/CrypticCreations
Author: Clutch_Reboot
Author-email: clutchshadow26@gmail.com
License: GNU General Public License v2.0
Keywords: dnd ciphers random CrypticCreations
Platform: UNKNOWN
Requires-Python: >=3.10
License-File: LICENSE
